addons/__init__.py
addons/chatgpt/__init__.py
addons/chatgpt/__main__.py
addons/chatgpt/chatgpt_service.py
addons/chatgpt/chatgpt_utils.py
addons/chatgpt/forms/__init__.py
addons/chatgpt/forms/study_level_form.py
addons/chatgpt/views/__init__.py
addons/chatgpt/views/ai_manual.py
addons/chatgpt/views/ai_route_of_study.py
addons/chatgpt/views/api_user.py
addons/chatgpt/views/chat.py
addons/chatgpt/views/yuanbian_chat_api.py
addons/chatgpt/views/yuanbian_helper.py
aliyunsdkafs/__init__.py
aliyunsdkafs/request/__init__.py
aliyunsdkafs/request/v20180112/AnalyzeNvcRequest.py
aliyunsdkafs/request/v20180112/AuthenticateSigRequest.py
aliyunsdkafs/request/v20180112/ConfigurationStyleRequest.py
aliyunsdkafs/request/v20180112/CreateConfigurationRequest.py
aliyunsdkafs/request/v20180112/DescribeCaptchaDayRequest.py
aliyunsdkafs/request/v20180112/DescribeCaptchaIpCityRequest.py
aliyunsdkafs/request/v20180112/DescribeCaptchaMinRequest.py
aliyunsdkafs/request/v20180112/DescribeCaptchaRiskRequest.py
aliyunsdkafs/request/v20180112/DescribeConfigNameRequest.py
aliyunsdkafs/request/v20180112/DescribeEarlyWarningRequest.py
aliyunsdkafs/request/v20180112/DescribePersonMachineListRequest.py
aliyunsdkafs/request/v20180112/SetEarlyWarningRequest.py
aliyunsdkafs/request/v20180112/__init__.py
flask_elasticsearch/__init__.py
flask_elasticsearch/elasticsearch.py
flask_nosql/__init__.py
flask_nosql/memcache.py
flask_nosql/mongodb.py
flask_nosql/redis.py
xp_pay/__init__.py
xp_pay/alipay/__init__.py
xp_pay/alipay/create_pay.py
xp_pay/alipay/pay_example.py
xp_pay/wxpay/__init__.py
xp_pay/wxpay/create_pay.py
xp_pay/wxpay/utils.py
xp_pay/wxpay/wechatpay.py
xp_pay/wxpayv3/__init__.py
xp_pay/wxpayv3/create_pay.py
xp_pay/wxpayv3/utils.py
xp_pay/wxpayv3/wechatpay.py
xp_upload/__init__.py
xp_wechat/__init__.py
xp_wechat/utils.py
xp_wechat/wechat_message_api.py
xp_wechat/wechat_official_api.py
yuanbian_kms/__init__.py
yuanbian_kms/constant.py
yuanbian_kms/extensions.py
yuanbian_kms/filters.py
yuanbiankms-0.1.0.dist-info/METADATA
yuanbiankms-0.1.0.dist-info/WHEEL
yuanbiankms-0.1.0.dist-info/entry_points.txt
yuanbiankms-0.1.0.dist-info/top_level.txt
yuanbiankms-0.1.0.dist-info/RECORD
