Metadata-Version: 2.4
Name: YuanbianKMS
Version: 0.1.0
Requires-Dist: flask
Requires-Dist: flask-login
Requires-Dist: flask-sqlalchemy
Requires-Dist: flask-jwt
Dynamic: requires-dist
